tos/__init__.py
tos/admin.py
tos/apps.py
tos/middleware.py
tos/models.py
tos/signal_handlers.py
tos/urls.py
tos/views.py
tos/migrations/0001_initial.py
tos/migrations/__init__.py
tos/templates/tos/tos.html
tos/templates/tos/tos_check.html
tos/templatetags/__init__.py
tos/templatetags/compat.py
tos/tests/__init__.py
tos/tests/test_middleware.py
tos/tests/test_models.py
tos/tests/test_urls.py
tos/tests/test_views.py
tos_i18n/__init__.py
tos_i18n/admin.py
tos_i18n/models.py
tos_i18n/tests.py
tos_i18n/translation.py
tos_i18n/views.py
django_tos-1.1.0.dist-info/AUTHORS.txt
django_tos-1.1.0.dist-info/LICENSE.txt
django_tos-1.1.0.dist-info/METADATA
django_tos-1.1.0.dist-info/WHEEL
django_tos-1.1.0.dist-info/top_level.txt
django_tos-1.1.0.dist-info/RECORD
