Metadata-Version: 2.1
Name: django-tos
Version: 1.1.0
Summary: django-tos is a reusable Django application for setting Terms of Service.
Home-page: http://github.com/revsys/django-tos/tree/master
Author: Frank Wiles
Author-email: frank@revsys.com
Classifier: Development Status :: 4 - Beta
Classifier: Environment :: Web Environment
Classifier: Intended Audience :: Developers
Classifier: License :: OSI Approved :: BSD License
Classifier: Operating System :: OS Independent
Classifier: Programming Language :: Python
Classifier: Framework :: Django
License-File: LICENSE.txt
License-File: AUTHORS.txt
